{"Reviews": [{"Title": "great product", "Author": "tottsm", "ReviewID": "R1RV5RSTJYLPQO", "Overall": "5.0", "Content": "this product is awesome, lot of features and  the quality of the photos and videos are astounding its worth the price", "Date": "June 7, 2014"}, {"Title": "Ematic 9inch", "Author": "Jhbball24", "ReviewID": "R2WA78XHFB55S8", "Overall": "4.0", "Content": "Great price , has internet and application app capability ,if u need just internet its very handy, wish it had Bluetooth though, it's all good.", "Date": "March 1, 2014"}], "ProductInfo": {"Price": "$136.38", "Features": "Screen Size: 9\"\nOperating System: Android 4.1\nProcessor Type: ARM\nProcessor Model: Not Available\nProcessor Speed: 1.1GHz", "Name": "8 GB Tablet - 9\" - 1.10 GHz - Black", "ImgURL": "http://ecx.images-amazon.com/images/I/51qA1m-a1jL._SY300_.jpg", "ProductID": "B00F0R92M0"}}